dbt/__init__.py
dbt/dataflow_config/__init__.py
dbt/dataflow_config/secrets_manager.py
test_dataflow_dbt-0.0.7rc6.dist-info/METADATA
test_dataflow_dbt-0.0.7rc6.dist-info/WHEEL
test_dataflow_dbt-0.0.7rc6.dist-info/top_level.txt
test_dataflow_dbt-0.0.7rc6.dist-info/RECORD
