Metadata-Version: 2.4
Name: test-dataflow-dbt
Version: 0.0.7rc6
Summary: DBT customized for Dataflow
Home-page: https://github.com/Digital-Back-Office/dataflow-dbt
Author: Dataflow
Requires-Dist: dbt-core==1.9.3
Requires-Dist: dbt-postgres==1.9.0
Dynamic: author
Dynamic: home-page
Dynamic: requires-dist
Dynamic: summary
